enterprises/__init__.py
enterprises/admin.py
enterprises/apps.py
enterprises/forms.py
enterprises/management/__init__.py
enterprises/management/commands/__init__.py
enterprises/management/commands/populate_database.py
enterprises/migrations/0001_initial.py
enterprises/migrations/0002_frequentlyaskedquestion.py
enterprises/migrations/0003_add_faq_ordering_field.py
enterprises/migrations/0004_contactformsubmission_add_fields.py
enterprises/migrations/__init__.py
enterprises/models.py
enterprises/recaptcha.py
enterprises/static/css/about.css
enterprises/static/css/faqs.css
enterprises/static/css/footer.css
enterprises/static/css/forms.css
enterprises/static/css/general.css
enterprises/static/css/index.css
enterprises/static/css/menu.css
enterprises/static/css/thank-you.css
enterprises/static/favicon.ico
enterprises/static/img/consultation.jpg
enterprises/static/img/headshot.jpg
enterprises/static/img/logo.png
enterprises/static/js/animations.js
enterprises/static/js/general.js
enterprises/templates/admin/contact_submission.html
enterprises/templates/enterprises/about.html
enterprises/templates/enterprises/base.html
enterprises/templates/enterprises/contact-thank-you.html
enterprises/templates/enterprises/contact.html
enterprises/templates/enterprises/faqs.html
enterprises/templates/enterprises/index.html
enterprises/urls.py
enterprises/views.py
evanduke/__init__.py
evanduke/asgi.py
evanduke/settings.py
evanduke/urls.py
evanduke/wsgi.py
manage.py
poetry.lock
pyproject.toml
evanduke-1.0.4.dist-info/METADATA
evanduke-1.0.4.dist-info/WHEEL
evanduke-1.0.4.dist-info/RECORD
