Metadata-Version: 2.1
Name: evanduke
Version: 1.0.4
Summary: 
Author: Heather Duke
Author-email: heather@heathernoelduke.com
Requires-Python: >=3.11,<4.0
Classifier: Programming Language :: Python :: 3
Classifier: Programming Language :: Python :: 3.11
Requires-Dist: django (>=4.2,<5.0)
Requires-Dist: django-environ (>=0.10.0,<0.11.0)
Requires-Dist: google-cloud-recaptcha-enterprise (>=1.12.1,<2.0.0)
Requires-Dist: gunicorn (>=20.1,<23.0)
Requires-Dist: psycopg2-binary (>=2.9.6,<3.0.0)
Requires-Dist: sentry-sdk (>=1.30.0,<2.0.0)
